zevents/__init__.py
zevents/core.py
zevents/dispatch.py
zevents-0.2.9.dist-info/AUTHORS.rst
zevents-0.2.9.dist-info/LICENSE
zevents-0.2.9.dist-info/METADATA
zevents-0.2.9.dist-info/WHEEL
zevents-0.2.9.dist-info/top_level.txt
zevents-0.2.9.dist-info/RECORD
