Metadata-Version: 2.1
Name: zevents
Version: 0.2.9
Summary: Easy to use and generic events system.
Home-page: https://github.com/tchappui/zevents
Author: Thierry Chappuis
Author-email: thierry@chappuis.io
License: MIT license
Keywords: zevents
Platform: UNKNOWN
Classifier: Development Status :: 2 - Pre-Alpha
Classifier: Intended Audience :: Developers
Classifier: License :: OSI Approved :: MIT License
Classifier: Natural Language :: English
Classifier: Programming Language :: Python :: 3.5
Classifier: Programming Language :: Python :: 3.6
Classifier: Programming Language :: Python :: 3.7
